gym_mtsim/__init__.py
gym_mtsim/data/__init__.py
gym_mtsim/data/symbols_crypto.pkl
gym_mtsim/data/symbols_forex.pkl
gym_mtsim/data/symbols_mixed.pkl
gym_mtsim/data/symbols_stocks.pkl
gym_mtsim/envs/__init__.py
gym_mtsim/envs/mt_env.py
gym_mtsim/metatrader/__init__.py
gym_mtsim/metatrader/api.py
gym_mtsim/metatrader/interface.py
gym_mtsim/metatrader/symbol.py
gym_mtsim/simulator/__init__.py
gym_mtsim/simulator/exceptions.py
gym_mtsim/simulator/mt_simulator.py
gym_mtsim/simulator/order.py
gym_mtsim-2.0.0.dist-info/LICENSE
gym_mtsim-2.0.0.dist-info/METADATA
gym_mtsim-2.0.0.dist-info/WHEEL
gym_mtsim-2.0.0.dist-info/top_level.txt
gym_mtsim-2.0.0.dist-info/RECORD
